<?xml version="1.0" encoding="UTF-8"?>
<configuration>

    <!-- Console appender for development (default) -->
    <springProfile name="!prod">
        <appender name="CONSOLE" class="ch.qos.logback.core.ConsoleAppender">
            <encoder>
                <pattern>%d{yyyy-MM-dd HH:mm:ss} [%thread] %-5level %logger{36} - %msg%n</pattern>
            </encoder>
        </appender>

        <root level="INFO">
            <appender-ref ref="CONSOLE"/>
        </root>

        <logger name="com.bemobi.aicontrol" level="DEBUG"/>
    </springProfile>

    <!-- JSON appender for production -->
    <springProfile name="prod">
        <appender name="JSON_CONSOLE" class="ch.qos.logback.core.ConsoleAppender">
            <encoder class="net.logstash.logback.encoder.LogstashEncoder">
                <includeMdcKeyName>executionId</includeMdcKeyName>
                <includeMdcKeyName>toolName</includeMdcKeyName>
            </encoder>
        </appender>

        <root level="INFO">
            <appender-ref ref="JSON_CONSOLE"/>
        </root>

        <logger name="com.bemobi.aicontrol" level="INFO"/>
    </springProfile>

</configuration>
